_portaudiowpatch.cp313-win32.pyd
pyaudiowpatch/__init__.py
pyaudiowpatch/__main__.py
pyaudiowpatch-0.2.12.8.dist-info/licenses/LICENSE.txt
pyaudiowpatch-0.2.12.8.dist-info/METADATA
pyaudiowpatch-0.2.12.8.dist-info/WHEEL
pyaudiowpatch-0.2.12.8.dist-info/top_level.txt
pyaudiowpatch-0.2.12.8.dist-info/RECORD
