Metadata-Version: 2.1
Name: PyAudioWPatch
Version: 0.2.12.8
Summary: PortAudio fork with WASAPI loopback support
Home-page: https://github.com/s0d3s/PyAudioWPatch/
Author: Hubert Pham(S0D3S edition)
License: Apache-2.0 license
Classifier: Development Status :: 4 - Beta
Classifier: License :: OSI Approved :: Apache Software License
Classifier: Programming Language :: Python :: 3
Classifier: Topic :: Multimedia :: Sound/Audio
License-File: LICENSE.txt
Provides-Extra: test
Requires-Dist: numpy; extra == "test"
